CHANGES.md
CONTRIBUTORS.md
LICENCE.txt
MANIFEST.in
README.md
pyproject.toml
requirements.txt
setup.cfg
setup.py
EQcorrscan.egg-info/PKG-INFO
EQcorrscan.egg-info/SOURCES.txt
EQcorrscan.egg-info/dependency_links.txt
EQcorrscan.egg-info/requires.txt
EQcorrscan.egg-info/top_level.txt
eqcorrscan/__init__.py
eqcorrscan/core/__init__.py
eqcorrscan/core/lag_calc.py
eqcorrscan/core/subspace.py
eqcorrscan/core/template_gen.py
eqcorrscan/core/match_filter/__init__.py
eqcorrscan/core/match_filter/detection.py
eqcorrscan/core/match_filter/family.py
eqcorrscan/core/match_filter/matched_filter.py
eqcorrscan/core/match_filter/party.py
eqcorrscan/core/match_filter/template.py
eqcorrscan/core/match_filter/tribe.py
eqcorrscan/core/match_filter/helpers/__init__.py
eqcorrscan/core/match_filter/helpers/archive_access.py
eqcorrscan/core/match_filter/helpers/clients.py
eqcorrscan/core/match_filter/helpers/matched_filter.py
eqcorrscan/core/match_filter/helpers/processes.py
eqcorrscan/core/match_filter/helpers/tribe.py
eqcorrscan/doc/EQcorrscan_logo.ico
eqcorrscan/doc/EQcorrscan_logo.jpg
eqcorrscan/doc/EQcorrscan_logo.pdf
eqcorrscan/doc/EQcorrscan_logo.png
eqcorrscan/doc/EQcorrscan_logo.svg
eqcorrscan/doc/Makefile
eqcorrscan/doc/RCET_logo_transparent.png
eqcorrscan/doc/api.rst
eqcorrscan/doc/conf.py
eqcorrscan/doc/environment.yml
eqcorrscan/doc/faq.rst
eqcorrscan/doc/index.rst
eqcorrscan/doc/installation.rst
eqcorrscan/doc/intro.rst
eqcorrscan/doc/make.bat
eqcorrscan/doc/processing_flow.svg
eqcorrscan/doc/requirements.txt
eqcorrscan/doc/tutorial.rst
eqcorrscan/doc/updates.rst
eqcorrscan/doc/__pycache__/conf.cpython-35.pyc
eqcorrscan/doc/_ext/obspydoc.py
eqcorrscan/doc/_ext/__pycache__/obspydoc.cpython-35.pyc
eqcorrscan/doc/_ext/__pycache__/obspydoc.cpython-36.pyc
eqcorrscan/doc/_ext/__pycache__/obspydoc.cpython-37.pyc
eqcorrscan/doc/plots/detection_multiplot.png
eqcorrscan/doc/plots/multi_event_singlechan.png
eqcorrscan/doc/plots/plot_repicked.png
eqcorrscan/doc/plots/template_gen.from_client.png
eqcorrscan/doc/plots/triple_plot.png
eqcorrscan/doc/plots/twoD_seismplot-depth.png
eqcorrscan/doc/plots/xcorr_plot.png
eqcorrscan/doc/submodules/core.lag_calc.rst
