Metadata-Version: 2.1
Name: EQcorrscan
Version: 0.5.2
Summary: EQcorrscan - matched-filter earthquake detection and analysis
Home-page: https://github.com/eqcorrscan/EQcorrscan
Author: Calum Chamberlain
Author-email: calum.chamberlain@vuw.ac.nz
License: LGPL-3.0-or-later
Keywords: earthquake correlation detection match-filter
Classifier: Development Status :: 4 - Beta
Classifier: Intended Audience :: Science/Research
Classifier: Topic :: Scientific/Engineering
Classifier: Programming Language :: Python :: 3.10
Classifier: Programming Language :: Python :: 3.11
Classifier: Programming Language :: Python :: 3.12
Classifier: Programming Language :: Python :: 3.13
License-File: LICENCE.txt
Requires-Dist: matplotlib>=1.3.0
Requires-Dist: scipy>=1.10
Requires-Dist: bottleneck
Requires-Dist: obspy>=1.3.0
Requires-Dist: numpy>=1.22.2
Requires-Dist: h5py
